pycrfsuite/__init__.py
pycrfsuite/_dumpparser.py
pycrfsuite/_logparser.py
pycrfsuite/_pycrfsuite.cp311-win_amd64.pyd
python_crfsuite_openmp-1.1.3.dist-info/LICENSE.txt
python_crfsuite_openmp-1.1.3.dist-info/METADATA
python_crfsuite_openmp-1.1.3.dist-info/WHEEL
python_crfsuite_openmp-1.1.3.dist-info/top_level.txt
python_crfsuite_openmp-1.1.3.dist-info/RECORD
