Metadata-Version: 2.2
Name: python-crfsuite-openmp
Version: 1.1.3
Summary: Python binding for CRFsuite wih OpenMP build
Home-page: https://github.com/bratao/python-crfsuite
Author: Bruno Cabral, Terry Peng, Mikhail Korobov
Author-email: bruno@potelo.com.br, pengtaoo@gmail.com, kmike84@gmail.com
License: MIT
Classifier: Development Status :: 4 - Beta
Classifier: Intended Audience :: Developers
Classifier: Intended Audience :: Science/Research
Classifier: License :: OSI Approved :: MIT License
Classifier: Programming Language :: Cython
Classifier: Programming Language :: Python
Classifier: Programming Language :: Python :: 3.11
Classifier: Programming Language :: Python :: 3.12
Classifier: Topic :: Software Development
Classifier: Topic :: Software Development :: Libraries :: Python Modules
Classifier: Topic :: Scientific/Engineering
Classifier: Topic :: Scientific/Engineering :: Information Analysis
Classifier: Topic :: Text Processing :: Linguistic
Requires-Python: >=3.11
License-File: LICENSE.txt
Dynamic: author
Dynamic: author-email
Dynamic: classifier
Dynamic: description
Dynamic: home-page
Dynamic: license
Dynamic: requires-python
Dynamic: summary
